[
  {
    "test_name": "tests/txfr.test.ts__example tests__ensures simnet is well initalised",
    "contract_id": "ST1PQHQKV0RJXZFY1DGX8MNSNYVE3VGZJSRTPGZGM.txfr",
    "method": "trans",
    "args": [
      "'ST1SJ3DTE5DN7X54YDH5D64R3BCB6A2AG2ZQ8YPD5"
    ],
    "cost_result": {
      "total": {
        "write_length": 1,
        "write_count": 2,
        "read_length": 101637,
        "read_count": 8,
        "runtime": 105684
      },
      "limit": {
        "write_length": 15000000,
        "write_count": 15000,
        "read_length": 100000000,
        "read_count": 15000,
        "runtime": 5000000000
      },
      "memory": 0,
      "memory_limit": 100000000
    }
  }
]